LICENSE
MANIFEST.in
README.md
README.rst
setup.py
numpy_fracdiff/__init__.py
numpy_fracdiff/apply_weights.py
numpy_fracdiff/find_truncation.py
numpy_fracdiff/frac_weights.py
numpy_fracdiff/fracdiff_fn.py
numpy_fracdiff.egg-info/PKG-INFO
numpy_fracdiff.egg-info/SOURCES.txt
numpy_fracdiff.egg-info/dependency_links.txt
numpy_fracdiff.egg-info/requires.txt
numpy_fracdiff.egg-info/top_level.txt
numpy_fracdiff.egg-info/zip-safe
test/__init__.py
test/test_apply_weights.py
test/test_find_truncation.py
test/test_frac_weights.py
test/test_fracdiff_fn.py