Metadata-Version: 1.2
Name: numpy-fracdiff
Version: 0.3.3
Summary: Fractional Difference for Time Series
Home-page: http://github.com/ulf1/numpy-fracdiff
Author: Ulf Hamster
Author-email: 554c46@gmail.com
License: Apache License 2.0
Platform: UNKNOWN
Requires-Python: >=3.6
